ktime.py
ktime-0.2.dist-info/entry_points.txt
ktime-0.2.dist-info/WHEEL
ktime-0.2.dist-info/METADATA
ktime-0.2.dist-info/RECORD
