Metadata-Version: 2.1
Name: ktime
Version: 0.2
Summary: 4个关于时间的功能
Keywords: 
Author-email: jutooy <jutooy@qq.com>
Classifier: License :: OSI Approved :: Apache Software License
